lipkg/Rsa.py
lipkg/__init__.py
lipkg/apiUtils.py
lipkg/httpClient.py
lipkg/kaClient.py
lipkg/signa.py
lipkg/trash/rsa.py
lipkg-3.3.0.dist-info/LICENSE
lipkg-3.3.0.dist-info/METADATA
lipkg-3.3.0.dist-info/WHEEL
lipkg-3.3.0.dist-info/top_level.txt
lipkg-3.3.0.dist-info/RECORD
