Metadata-Version: 2.1
Name: lipkg
Version: 3.3.0
Summary: lipu de package
Author-email: lipu <lizhankangde@gmail.com>
Project-URL: Homepage, https://github.com/lizhankang/python-sdk
Project-URL: Issues, https://github.com/lizhankang/python-sdk/issues
Classifier: Programming Language :: Python :: 3
Classifier: License :: OSI Approved :: MIT License
Classifier: Operating System :: OS Independent
Requires-Python: >=3.0
License-File: LICENSE
Requires-Dist: rsa
Requires-Dist: requests
Requires-Dist: importlib-metadata
Requires-Dist: pycryptodome
Requires-Dist: pandas
Requires-Dist: openpyxl
Requires-Dist: faker
